{
    "bebe": [
        {
            "id": 1,
            "category": "Ajuares",
            "name": "Ajuar pima blanco con picot celeste",
            "brand": "Botonitos",
            "price": 34000,
            "description": "Ajuar pima blanco con picot celeste (body, ranita, gorrito)",
            "size": [
                "T1"
            ],
            "img": [
                "https://firebasestorage.googleapis.com/v0/b/images-cdwenz.appspot.com/o/AmuriDiMatri%2FBebe%2Fajuares%2F1_1.png?alt=media&token=b874e38f-daee-40fc-b2ff-5f8123b85ceb",
                "https://firebasestorage.googleapis.com/v0/b/images-cdwenz.appspot.com/o/AmuriDiMatri%2FBebe%2Fajuares%2F1_2.png?alt=media&token=08ab951a-34b9-4af9-9173-b740de771c8a"
            ]
        },
        {
            "id": 2,
            "category": "Ajuares",
            "name": "Ajuar pima liso (batita, ranita, gorrito)",
            "brand": "Botonitos",
            "price": 34000,
            "description": "Ajuar pima liso color natural (batita, ranita, gorrito)",
            "size": [
                "T1"
            ],
            "img": [
                "https://firebasestorage.googleapis.com/v0/b/images-cdwenz.appspot.com/o/AmuriDiMatri%2FBebe%2Fajuares%2F2_1.png?alt=media&token=b61a6bf4-6eb6-4fd2-8dc3-34d9966bcbb9"
            ]
        },
        {
            "id": 3,
            "category": "Ajuares",
            "name": "Ajuar pima elefante celeste",
            "brand": "Botonitos",
            "price": 34000,
            "description": "Ajuar pima elefante celeste",
            "size": [
                "T0",
                "T1"
            ],
            "img": [
                "https://firebasestorage.googleapis.com/v0/b/images-cdwenz.appspot.com/o/AmuriDiMatri%2FBebe%2Fajuares%2F3_1.png?alt=media&token=66e21a30-a8c0-4b0e-b49e-eef183a3f924",
                "https://firebasestorage.googleapis.com/v0/b/images-cdwenz.appspot.com/o/AmuriDiMatri%2FBebe%2Fajuares%2F3_2.png?alt=media&token=c4dfbd7c-9afe-45b1-9497-3e7cea9093ab"
            ]
        },
        {
            "id": 4,
            "category": "Ajuares",
            "name": "Ajuar pima nautico",
            "brand": "Botonitos",
            "price": 34000,
            "description": "Ajuar pima nautico (body, ranita, gorrito)",
            "size": [
                "T0",
                "T1"
            ],
            "img": [
                "https://firebasestorage.googleapis.com/v0/b/images-cdwenz.appspot.com/o/AmuriDiMatri%2FBebe%2Fajuares%2F4_1.png?alt=media&token=6d6d454e-6f7e-4a03-85e8-3a2b995aa5fa",
                "https://firebasestorage.googleapis.com/v0/b/images-cdwenz.appspot.com/o/AmuriDiMatri%2FBebe%2Fajuares%2F4_2.png?alt=media&token=bf560200-b2ef-46bf-9053-1fd58eb1a085"
            ]
        },
        {
            "id": 5,
            "category": "Ajuares",
            "name": "Ajuar pima safari",
            "brand": "Botonitos",
            "price": 34000,
            "description": "Ajuar pima safari (batita, ranita, gorrito)",
            "size": [
                "T0",
                "T1"
            ],
            "img": [
                "https://firebasestorage.googleapis.com/v0/b/images-cdwenz.appspot.com/o/AmuriDiMatri%2FBebe%2Fajuares%2F5_1.png?alt=media&token=80576172-ef0a-4a45-b69c-4b2e921609ee"
            ]
        },
        {
            "id": 6,
            "category": "Ajuares",
            "name": "Ajuar pima raya natural",
            "brand": "Botonitos",
            "price": 34000,
            "description": "Ajuar pima raya natural (batita, ranita, gorrito)",
            "size": [
                "T0",
                "T1"
            ],
            "img": [
                "https://firebasestorage.googleapis.com/v0/b/images-cdwenz.appspot.com/o/AmuriDiMatri%2FBebe%2Fajuares%2F6_1.png?alt=media&token=20c5825a-95ad-4ce1-a10a-30b2a6f51305"
            ]
        },
        {
            "id": 7,
            "category": "Ajuares",
            "name": "Ajuar bordado cavallito madera",
            "brand": "Globito",
            "price": 35000,
            "description": "Ajuar bordado cavallito madera con caja (body, pantalon, gorrito)",
            "size": [
                "T0"
            ],
            "img": [
                "https://firebasestorage.googleapis.com/v0/b/images-cdwenz.appspot.com/o/AmuriDiMatri%2FBebe%2Fajuares%2F7_1.png?alt=media&token=421520a8-d1c0-4637-b143-e8aa93774850",
                "https://firebasestorage.googleapis.com/v0/b/images-cdwenz.appspot.com/o/AmuriDiMatri%2FBebe%2Fajuares%2F7_2.png?alt=media&token=03581bf4-b2b0-4fcc-9b78-36ff17aa5548",
                "https://firebasestorage.googleapis.com/v0/b/images-cdwenz.appspot.com/o/AmuriDiMatri%2FBebe%2Fajuares%2F7_3.png?alt=media&token=572dd545-00c6-4db1-99f8-9688f34a1427"
            ]
        },
        {
            "id": 8,
            "category": "Ajuares",
            "name": "Ajuar bordado conejo",
            "brand": "Globito",
            "price": 35000,
            "description": "Ajuar bordado conejo con caja (body, pantalon, gorrito)",
            "size": [
                "T0",
                "T1"
            ],
            "img": [
                "https://firebasestorage.googleapis.com/v0/b/images-cdwenz.appspot.com/o/AmuriDiMatri%2FBebe%2Fajuares%2F8_1.png?alt=media&token=9553d656-43aa-4322-9c0c-372c6663e6fd",
                "https://firebasestorage.googleapis.com/v0/b/images-cdwenz.appspot.com/o/AmuriDiMatri%2FBebe%2Fajuares%2F8_2.png?alt=media&token=8cbbbbc0-7adb-4e9d-9722-94f6de88eaaa"
            ]
        },
        {
            "id": 9,
            "category": "Ajuares",
            "name": "Ajuar pima blanco",
            "brand": "Botonitos",
            "price": 34000,
            "description": "Ajuar pima blanco (batita, ranita, gorrito)",
            "size": [
                "T1"
            ],
            "img": [
                "https://firebasestorage.googleapis.com/v0/b/images-cdwenz.appspot.com/o/AmuriDiMatri%2FBebe%2Fajuares%2F9_1.png?alt=media&token=504e9748-a5de-4b0f-a807-b4a901485817"
            ]
        },
        {
            "id": 11,
            "category": "Bodies",
            "name": "Body de jersey de algodon con cuello polo Lucas",
            "brand": "Magdalena Esposito",
            "price": 40000,
            "description": "Body de jersey de algodon con cuello polo Lucas",
            "size": [
                "12M"
            ],
            "img": [
                "https://firebasestorage.googleapis.com/v0/b/images-cdwenz.appspot.com/o/AmuriDiMatri%2FBebe%2Fbodies%2F11_1.png?alt=media&token=d6796201-2620-49bf-8a55-9687ae1dcd03"
            ]
        },
        {
            "id": 12,
            "category": "Bodies",
            "name": "Body de jersey de algodon con cuello polo Lucas",
            "brand": "Magdalena Esposito",
            "price": 40000,
            "description": "Body de jersey de algodon con cuello polo Lucas",
            "size": [
                "12M"
            ],
            "img": [
                "https://firebasestorage.googleapis.com/v0/b/images-cdwenz.appspot.com/o/AmuriDiMatri%2FBebe%2Fbodies%2F12_1.png?alt=media&token=949267ec-1d8a-4253-a3cf-b514e44d6fbc"
            ]
        },
        {
            "id": 13,
            "category": "Bodies",
            "name": "Body de jersey de algodon con cuello polo Lucas",
            "brand": "Magdalena Esposito",
            "price": 40000,
            "description": "Body de jersey de algodon con cuello polo Lucas",
            "size": [
                "9M",
                "12M",
                "18M"
            ],
            "img": [
                "https://firebasestorage.googleapis.com/v0/b/images-cdwenz.appspot.com/o/AmuriDiMatri%2FBebe%2Fbodies%2F13_1.png?alt=media&token=6d55772c-bf43-419d-a80a-a05e1a2d93c2"
            ]
        },
        {
            "id": 14,
            "category": "Bodies",
            "name": "Body camisa de jersey de algodon con cuello polo Pier",
            "brand": "Magdalena Esposito",
            "price": 45000,
            "description": "Body camisa de jersey de algodon con cuello polo Pier",
            "size": [
                "3M",
                "6M",
                "24M"
            ],
            "img": [
                "https://firebasestorage.googleapis.com/v0/b/images-cdwenz.appspot.com/o/AmuriDiMatri%2FBebe%2Fbodies%2F14_1.png?alt=media&token=67de4394-93e2-4a33-b2a3-273d271c2770"
            ]
        },
        {
            "id": 15,
            "category": "Bodies",
            "name": "Body de jersey de algodon con cuello y puno tejido Giorgio",
            "brand": "Magdalena Esposito",
            "price": 40000,
            "description": "Body de jersey de algodon con cuello y puno tejido Giorgio",
            "size": [
                "12M"
            ],
            "img": [
                "https://firebasestorage.googleapis.com/v0/b/images-cdwenz.appspot.com/o/AmuriDiMatri%2FBebe%2Fbodies%2F15_1.png?alt=media&token=e00e568d-4068-4cee-9f93-6aaf22be4f59"
            ]
        },
        {
            "id": 16,
            "category": "Bodies",
            "name": "Body camisa manga corta Vito",
            "brand": "Magdalena Esposito",
            "price": 65000,
            "description": "Body camisa manga corta Vito",
            "size": [
                "3M",
                "6M",
                "9M",
                "12M",
                "18M"
            ],
            "img": [
                "https://firebasestorage.googleapis.com/v0/b/images-cdwenz.appspot.com/o/AmuriDiMatri%2FBebe%2Fbodies%2F16_1.png?alt=media&token=76406ce6-7666-4deb-b3d7-54a67f379849"
            ]
        },
        {
            "id": 20,
            "category": "Bodies",
            "name": "Body pique polo",
            "brand": "Old Bunch",
            "price": 35000,
            "description": "Body pique polo",
            "size": [
                "3M",
                "6M",
                "9M"
            ],
            "img": [
                "https://firebasestorage.googleapis.com/v0/b/images-cdwenz.appspot.com/o/AmuriDiMatri%2FBebe%2Fbodies%2F20_1.png?alt=media&token=76a52581-e934-41c8-9474-3a6a8d5ec589"
            ]
        },
        {
            "id": 21,
            "category": "Bodies",
            "name": "Body polo barquito",
            "brand": "Old Bunch",
            "price": 35000,
            "description": "Body polo barquito",
            "size": [
                "9M"
            ],
            "img": [
                "https://firebasestorage.googleapis.com/v0/b/images-cdwenz.appspot.com/o/AmuriDiMatri%2FBebe%2Fbodies%2F21_1.png?alt=media&token=007b9af9-704c-4994-91c5-72d502196233"
            ]
        },
        {
            "id": 22,
            "category": "Bodies",
            "name": "Body polo ancla",
            "brand": "Old Bunch",
            "price": 35000,
            "description": "Body polo ancla",
            "size": [
                "3M",
                "9M"
            ],
            "img": [
                "https://firebasestorage.googleapis.com/v0/b/images-cdwenz.appspot.com/o/AmuriDiMatri%2FBebe%2Fbodies%2F22_1.png?alt=media&token=992cffb8-6f73-45de-8f0c-bbb15673d821"
            ]
        },
        {
            "id": 23,
            "category": "Bodies",
            "name": "Body bordado barquito",
            "brand": "Old Bunch",
            "price": 35000,
            "description": "Body bordado barquito",
            "size": [
                "12M"
            ],
            "img": [
                "https://firebasestorage.googleapis.com/v0/b/images-cdwenz.appspot.com/o/AmuriDiMatri%2FBebe%2Fbodies%2F23_1.png?alt=media&token=fc55f1e0-2d1b-4a27-9a82-892b4c4be8a2"
            ]
        },
        {
            "id": 24,
            "category": "Bodies",
            "name": "Body polo barquito",
            "brand": "Old Bunch",
            "price": 35000,
            "description": "Body polo barquito",
            "size": [
                "2A"
            ],
            "img": [
                "https://firebasestorage.googleapis.com/v0/b/images-cdwenz.appspot.com/o/AmuriDiMatri%2FBebe%2Fbodies%2F24_1.png?alt=media&token=6fc291b2-18ce-4514-85e3-ee9766769daf"
            ]
        },
        {
            "id": 25,
            "category": "Bodies",
            "name": "Body bordado osito",
            "brand": "Old Bunch",
            "price": 30000,
            "description": "Body bordado osito celeste",
            "size": [
                "6M",
                "9M"
            ],
            "img": [
                "https://firebasestorage.googleapis.com/v0/b/images-cdwenz.appspot.com/o/AmuriDiMatri%2FBebe%2Fbodies%2F25_1.png?alt=media&token=15ce7daf-c4ef-4847-a0c0-463b8ac4a7ef"
            ]
        },
        {
            "id": 26,
            "category": "Bodies",
            "name": "Body bordado barquitos",
            "brand": "Old Bunch",
            "price": 30000,
            "description": "Body bordado barquitos celeste",
            "size": [
                "6M",
                "9M"
            ],
            "img": [
                "https://firebasestorage.googleapis.com/v0/b/images-cdwenz.appspot.com/o/AmuriDiMatri%2FBebe%2Fbodies%2F26_1.png?alt=media&token=a37f24f2-5de2-4eea-a21a-9b9ce20f6e65"
            ]
        },
        {
            "id": 27,
            "category": "Bodies",
            "name": "Body de pima manga larga",
            "brand": "Babytime",
            "price": 25000,
            "description": "Body de pima manga larga celeste",
            "size": [
                "3M"
            ],
            "img": [
                "https://firebasestorage.googleapis.com/v0/b/images-cdwenz.appspot.com/o/AmuriDiMatri%2FBebe%2Fbodies%2F27_1.png?alt=media&token=3b33d775-5503-4c76-99e5-05cd4268e3e6"
            ]
        },
        {
            "id": 29,
            "category": "Enteritos",
            "name": "Enterito pima nautico",
            "brand": "Botonitos",
            "price": 32000,
            "description": "Enterito pima nautico cuello tejido",
            "size": [
                "T1",
                "T2"
            ],
            "img": [
                "https://firebasestorage.googleapis.com/v0/b/images-cdwenz.appspot.com/o/AmuriDiMatri%2FBebe%2Fenteritos%2F29_1.png?alt=media&token=56b31dc2-8b1b-4e6f-bdd8-36de55b4e01e",
                "https://firebasestorage.googleapis.com/v0/b/images-cdwenz.appspot.com/o/AmuriDiMatri%2FBebe%2Fenteritos%2F29_2.png?alt=media&token=3c20ca5c-9cef-4245-84e7-b0f9f9d3ac1c"
            ]
        },
        {
            "id": 30,
            "category": "Enteritos",
            "name": "Enterito pima nautico costado",
            "brand": "Botonitos",
            "price": 32000,
            "description": "Enterito pima nautico ab costado",
            "size": [
                "T1",
                "T2"
            ],
            "img": [
                "https://firebasestorage.googleapis.com/v0/b/images-cdwenz.appspot.com/o/AmuriDiMatri%2FBebe%2Fenteritos%2F30_1.png?alt=media&token=cffa2c67-0ca6-4613-8a62-4188fb33ed49",
                "https://firebasestorage.googleapis.com/v0/b/images-cdwenz.appspot.com/o/AmuriDiMatri%2FBebe%2Fenteritos%2F30_2.png?alt=media&token=86bb6ea2-8161-4e1c-adb0-bfc6b0d67359"
            ]
        },
        {
            "id": 31,
            "category": "Enteritos",
            "name": "Enterito combinado bordado castor",
            "brand": "Globito",
            "price": 35000,
            "description": "Enterito combinado bordado castor",
            "size": [
                "T1"
            ],
            "img": [
                "https://firebasestorage.googleapis.com/v0/b/images-cdwenz.appspot.com/o/AmuriDiMatri%2FBebe%2Fenteritos%2F31_1.png?alt=media&token=761a6614-25e6-4f87-bfcb-3408c9bd253e"
            ]
        },
        {
            "id": 32,
            "category": "Enteritos",
            "name": "Enterito ballena",
            "brand": "Globito",
            "price": 30000,
            "description": "Enterito sin mangas ballena",
            "size": [
                "T0",
                "T2"
            ],
            "img": [
                "https://firebasestorage.googleapis.com/v0/b/images-cdwenz.appspot.com/o/AmuriDiMatri%2FBebe%2Fenteritos%2F32_1.png?alt=media&token=765aace2-f48e-413d-a403-0754480d34d3"
            ]
        },
        {
            "id": 33,
            "category": "Conjuntos",
            "name": "Conjunto chomba nautico y short azul",
            "brand": "Botonitos",
            "price": 36000,
            "description": "Chomba nautico y short azul",
            "size": [
                "T1",
                "T2"
            ],
            "img": [
                "https://firebasestorage.googleapis.com/v0/b/images-cdwenz.appspot.com/o/AmuriDiMatri%2FBebe%2Fconjuntos%2F33_1.png?alt=media&token=85c4961c-3d57-43ee-b2c1-85c500b3ad5d",
                "https://firebasestorage.googleapis.com/v0/b/images-cdwenz.appspot.com/o/AmuriDiMatri%2FBebe%2Fconjuntos%2F33_2.png?alt=media&token=ae17f3fc-f650-4f76-a3ad-a135fea0206e"
            ]
        },
        {
            "id": 34,
            "category": "Conjuntos",
            "name": "Conjunto chomba huellita gris y short gris",
            "brand": "Botonitos",
            "price": 36000,
            "description": "Chomba huellita gris y short gris",
            "size": [
                "T1",
                "T2"
            ],
            "img": [
                "https://firebasestorage.googleapis.com/v0/b/images-cdwenz.appspot.com/o/AmuriDiMatri%2FBebe%2Fconjuntos%2F34_1.png?alt=media&token=2d09c50d-eeaa-4573-9151-0969337878f0",
                "https://firebasestorage.googleapis.com/v0/b/images-cdwenz.appspot.com/o/AmuriDiMatri%2FBebe%2Fconjuntos%2F34_2.png?alt=media&token=1aa450e6-c220-458d-9d60-ee00a3a42bac"
            ]
        },
        {
            "id": 35,
            "category": "Conjuntos",
            "name": "Conjunto bordado buceo",
            "brand": "Globito",
            "price": 36000,
            "description": "Conjunto body y pantalon bordado buceo",
            "size": [
                "T00",
                "T1",
                "T2"
            ],
            "img": [
                "https://firebasestorage.googleapis.com/v0/b/images-cdwenz.appspot.com/o/AmuriDiMatri%2FBebe%2Fconjuntos%2F35_1.png?alt=media&token=266c27c8-32a4-4b36-9dc9-fc8c208205d4",
                "https://firebasestorage.googleapis.com/v0/b/images-cdwenz.appspot.com/o/AmuriDiMatri%2FBebe%2Fconjuntos%2F35_2.png?alt=media&token=1fc64979-4748-4b01-b573-3354c760fa63"
            ]
        },
        {
            "id": 36,
            "category": "Conjuntos",
            "name": "Conjunto beach ballenas",
            "brand": "Globito",
            "price": 38000,
            "description": "Conjunto body americano y pantalon beach ballenas",
            "size": [
                "T0",
                "T1",
                "T2"
            ],
            "img": [
                "https://firebasestorage.googleapis.com/v0/b/images-cdwenz.appspot.com/o/AmuriDiMatri%2FBebe%2Fconjuntos%2F36_1.png?alt=media&token=1f0f72ed-9b9c-4372-8a99-942abf2ee088",
                "https://firebasestorage.googleapis.com/v0/b/images-cdwenz.appspot.com/o/AmuriDiMatri%2FBebe%2Fconjuntos%2F36_2.png?alt=media&token=fa7422e9-ea4d-4834-bc77-34065152fed6"
            ]
        },
        {
            "id": 37,
            "category": "Conjuntos",
            "name": "Conjunto lino bordado marinero",
            "brand": "Globito",
            "price": 38000,
            "description": "Conjunto lino bordado marinero (remera, pantalones)",
            "size": [
                "0M"
            ],
            "img": [
                "https://firebasestorage.googleapis.com/v0/b/images-cdwenz.appspot.com/o/AmuriDiMatri%2FBebe%2Fconjuntos%2F37_1.png?alt=media&token=04e36bdd-1bf9-43a2-b5ec-dddae3b4ce9f"
            ]
        },
        {
            "id": 38,
            "category": "Conjuntos",
            "name": "Conjunto lino bordado banderines",
            "brand": "Globito",
            "price": 45000,
            "description": "Conjunto lino bordado oso con banderines (remera, pantalones)",
            "size": [
                "6M",
                "9M"
            ],
            "img": [
                "https://firebasestorage.googleapis.com/v0/b/images-cdwenz.appspot.com/o/AmuriDiMatri%2FBebe%2Fconjuntos%2F38_1.png?alt=media&token=4442aeee-b5f2-4d11-a627-367cc3b229d3",
                "https://firebasestorage.googleapis.com/v0/b/images-cdwenz.appspot.com/o/AmuriDiMatri%2FBebe%2Fconjuntos%2F38_2.png?alt=media&token=2e2076b1-f132-4308-94d5-207e743ebd06"
            ]
        },
        {
            "id": 39,
            "category": "Conjuntos",
            "name": "Conjunto bordado gato",
            "brand": "Globito",
            "price": 42000,
            "description": "Conjunto 3 piezas bordado con rayas (body, pantalon, gorrito)",
            "size": [
                "T0",
                "T1"
            ],
            "img": [
                "https://firebasestorage.googleapis.com/v0/b/images-cdwenz.appspot.com/o/AmuriDiMatri%2FBebe%2Fconjuntos%2F39_1.png?alt=media&token=265c4d31-55ab-4784-8c4f-c342adb85da6"
            ]
        },
        {
            "id": 40,
            "category": "Conjuntos",
            "name": "Conjunto jardinero c/ body",
            "brand": "Globito",
            "price": 36000,
            "description": "Conjunto jardinero con body rayado",
            "size": [
                "T0"
            ],
            "img": [
                "https://firebasestorage.googleapis.com/v0/b/images-cdwenz.appspot.com/o/AmuriDiMatri%2FBebe%2Fconjuntos%2F40_1.png?alt=media&token=a3e1f686-b738-4c2e-862e-b32863661358"
            ]
        },
        {
            "id": 41,
            "category": "Conjuntos",
            "name": "Conjunto en viyela de camisaco escoces con pantalon Mateo",
            "brand": "Magdalena Esposito",
            "price": 80000,
            "description": "Conjunto en viyela de camisaco escoces con pantalon Mateo",
            "size": [
                "12M",
                "24M"
            ],
            "img": [
                "https://firebasestorage.googleapis.com/v0/b/images-cdwenz.appspot.com/o/AmuriDiMatri%2FBebe%2Fconjuntos%2F41_1.png?alt=media&token=d8f157e4-22f9-4c38-9cf0-f956e02da0f5"
            ]
        },
        {
            "id": 43,
            "category": "Conjuntos",
            "name": "Conjunto 3P bordado oso",
            "brand": "Globito",
            "price": 45000,
            "description": "Conjunto 3 piezas bordado oso (remera, pantalon, campera)",
            "size": [
                "0M",
                "3M",
                "6M"
            ],
            "img": [
                "https://firebasestorage.googleapis.com/v0/b/images-cdwenz.appspot.com/o/AmuriDiMatri%2FBebe%2Fconjuntos%2F43_1.png?alt=media&token=ede0d12e-2826-497b-83d3-3333d6ea7699"
            ]
        },
        {
            "id": 45,
            "category": "Conjuntos",
            "name": "Conjunto 3P bordado perrito",
            "brand": "Globito",
            "price": 45000,
            "description": "Conjunto 3 piezas bordado perrito (body, pantalon, campera)",
            "size": [
                "T0"
            ],
            "img": [
                "https://firebasestorage.googleapis.com/v0/b/images-cdwenz.appspot.com/o/AmuriDiMatri%2FBebe%2Fconjuntos%2F45_1.png?alt=media&token=7defb5d0-fc8f-40ae-bcab-1c7cbafb2041"
            ]
        },
        {
            "id": 47,
            "category": "Conjuntos",
            "name": "Conjunto bordado perrito plush",
            "brand": "Globito",
            "price": 42000,
            "description": "Conjunto 2 piezas bordado perrito plush (body, jardinero)",
            "size": [
                "6M",
                "9M"
            ],
            "img": [
                "https://firebasestorage.googleapis.com/v0/b/images-cdwenz.appspot.com/o/AmuriDiMatri%2FBebe%2Fconjuntos%2F47_1.png?alt=media&token=f6f287f6-a4ec-433d-a565-aed33deaa3e8"
            ]
        },
        {
            "id": 48,
            "category": "Conjuntos",
            "name": "Conjunto bordado oso plush",
            "brand": "Globito",
            "price": 42000,
            "description": "Conjunto 2 piezas bordado oso plush (body, jardinero)",
            "size": [
                "6M",
                "9M"
            ],
            "img": [
                "https://firebasestorage.googleapis.com/v0/b/images-cdwenz.appspot.com/o/AmuriDiMatri%2FBebe%2Fconjuntos%2F48_1.png?alt=media&token=1a17412b-5936-47b7-88ca-b4b07b54a020"
            ]
        },
        {
            "id": 50,
            "category": "Conjuntos",
            "name": "Conjunto 3P bordado animales",
            "brand": "Globito",
            "price": 38000,
            "description": "Conjunto 3 piezas bordado animales (body, ranita, gorrito)",
            "size": [
                "T0"
            ],
            "img": [
                "https://firebasestorage.googleapis.com/v0/b/images-cdwenz.appspot.com/o/AmuriDiMatri%2FBebe%2Fconjuntos%2F50_1.png?alt=media&token=e1088d7a-341c-4065-8cf3-2f533a2de3a6"
            ]
        },
        {
            "id": 52,
            "category": "Conjuntos",
            "name": "Conjunto 3P nido de abeja",
            "brand": "Globito",
            "price": 40000,
            "description": "Conjunto 3 piezas nido de abeja (remera, pantalon, campera)",
            "size": [
                "3M",
                "6M",
                "9M",
                "12M"
            ],
            "img": [
                "https://firebasestorage.googleapis.com/v0/b/images-cdwenz.appspot.com/o/AmuriDiMatri%2FBebe%2Fconjuntos%2F52_1.png?alt=media&token=67a552a2-8ca1-46ff-868d-f54648fd9923",
                "https://firebasestorage.googleapis.com/v0/b/images-cdwenz.appspot.com/o/AmuriDiMatri%2FBebe%2Fconjuntos%2F52_2.png?alt=media&token=b0f3b56a-aee3-4f16-8349-a85be1d9ecba",
                "https://firebasestorage.googleapis.com/v0/b/images-cdwenz.appspot.com/o/AmuriDiMatri%2FBebe%2Fconjuntos%2F52_3.png?alt=media&token=edb0a13b-3a64-4993-9750-1da27cb76b73"
            ]
        },
        {
            "id": 53,
            "category": "Conjuntos",
            "name": "Conjunto 3P rustico",
            "brand": "Globito",
            "price": 50000,
            "description": "Conjunto 3 piezas rustico (remera, pantalon, campera)",
            "size": [
                "3M",
                "6M",
                "9M"
            ],
            "img": [
                "https://firebasestorage.googleapis.com/v0/b/images-cdwenz.appspot.com/o/AmuriDiMatri%2FBebe%2Fconjuntos%2F53_1.png?alt=media&token=2a2a9806-5c50-4772-becb-42df67a3b081",
                "https://firebasestorage.googleapis.com/v0/b/images-cdwenz.appspot.com/o/AmuriDiMatri%2FBebe%2Fconjuntos%2F53_2.png?alt=media&token=23702e59-6595-44a2-a053-aedab6edc30d",
                "https://firebasestorage.googleapis.com/v0/b/images-cdwenz.appspot.com/o/AmuriDiMatri%2FBebe%2Fconjuntos%2F53_3.png?alt=media&token=583ef563-8641-44ad-bff0-9f518734326f"
            ]
        },
        {
            "id": 54,
            "category": "Conjuntos",
            "name": "Conjunto jardinero c/ body",
            "brand": "Globito",
            "price": 42000,
            "description": "Conjunto 2 piezas rustico (jardinero, body)",
            "size": [
                "3M",
                "6M",
                "9M"
            ],
            "img": [
                "https://firebasestorage.googleapis.com/v0/b/images-cdwenz.appspot.com/o/AmuriDiMatri%2FBebe%2Fconjuntos%2F54_1.png?alt=media&token=335b1167-7b0f-4516-bfab-28fd3907f760",
                "https://firebasestorage.googleapis.com/v0/b/images-cdwenz.appspot.com/o/AmuriDiMatri%2FBebe%2Fconjuntos%2F54_2.png?alt=media&token=a8639b36-5efd-4833-b461-c084fb16aee5",
                "https://firebasestorage.googleapis.com/v0/b/images-cdwenz.appspot.com/o/AmuriDiMatri%2FBebe%2Fconjuntos%2F54_3.png?alt=media&token=2a7ffdc8-ccd0-42ac-8109-70c02bc6fb6a"
            ]
        },
        {
            "id": 55,
            "category": "Conjuntos",
            "name": "Conjunto lino bordado banderines",
            "brand": "Globito",
            "price": 45000,
            "description": "Conjunto lino bordado oso con banderines (remera, pantalones)",
            "size": [
                "9M",
                "12M"
            ],
            "img": [
                "https://firebasestorage.googleapis.com/v0/b/images-cdwenz.appspot.com/o/AmuriDiMatri%2FBebe%2Fconjuntos%2F55_1.png?alt=media&token=5f204278-8430-40de-b65b-677e21b08f56",
                "https://firebasestorage.googleapis.com/v0/b/images-cdwenz.appspot.com/o/AmuriDiMatri%2FBebe%2Fconjuntos%2F55_2.png?alt=media&token=06ff23c3-9ea1-4e91-b8e5-aed720007e73",
                "https://firebasestorage.googleapis.com/v0/b/images-cdwenz.appspot.com/o/AmuriDiMatri%2FBebe%2Fconjuntos%2F55_3.png?alt=media&token=105d85c7-2b44-4399-add5-33e6d1b4ae01"
            ]
        },
        {
            "id": 56,
            "category": "Conjuntos",
            "name": "Conjunto lino bordado marinero",
            "brand": "Globito",
            "price": 38000,
            "description": "Conjunto lino bordado marinero (remera, pantalones)",
            "size": [
                "3M",
                "6M"
            ],
            "img": [
                "https://firebasestorage.googleapis.com/v0/b/images-cdwenz.appspot.com/o/AmuriDiMatri%2FBebe%2Fconjuntos%2F56_1.png?alt=media&token=3784a5e1-f117-4211-ac8a-28846bcf302d",
                "https://firebasestorage.googleapis.com/v0/b/images-cdwenz.appspot.com/o/AmuriDiMatri%2FBebe%2Fconjuntos%2F56_2.png?alt=media&token=edcf3907-2168-4c79-8fc8-8b4dfc0d06c1",
                "https://firebasestorage.googleapis.com/v0/b/images-cdwenz.appspot.com/o/AmuriDiMatri%2FBebe%2Fconjuntos%2F56_3.png?alt=media&token=f074205a-5f6b-4adb-9b61-d0da86388850"
            ]
        },
        {
            "id": 57,
            "category": "Conjuntos",
            "name": "Conjunto 3P bordado osito",
            "brand": "Globito",
            "price": 38000,
            "description": "Conjunto 3 piezas bordado osito (body, pantalon, gorrito)",
            "size": [
                "T0",
                "T1"
            ],
            "img": [
                "https://firebasestorage.googleapis.com/v0/b/images-cdwenz.appspot.com/o/AmuriDiMatri%2FBebe%2Fconjuntos%2F56_3.png?alt=media&token=f074205a-5f6b-4adb-9b61-d0da86388850",
                "https://firebasestorage.googleapis.com/v0/b/images-cdwenz.appspot.com/o/AmuriDiMatri%2FBebe%2Fconjuntos%2F57_2.png?alt=media&token=3ad71123-f4e5-4da1-a380-f4742bfbe562"
            ]
        },
        {
            "id": 58,
            "category": "Conjuntos",
            "name": "Conjunto 2P c/ body cuello mao",
            "brand": "Globito",
            "price": 38000,
            "description": "Conjunto 2 piezas con body cuello mao (body, pantalon)",
            "size": [
                "T0",
                "T1"
            ],
            "img": [
                "https://firebasestorage.googleapis.com/v0/b/images-cdwenz.appspot.com/o/AmuriDiMatri%2FBebe%2Fconjuntos%2F58_1.png?alt=media&token=1ec82089-e7ea-410e-b72e-7f284f391eab",
                "https://firebasestorage.googleapis.com/v0/b/images-cdwenz.appspot.com/o/AmuriDiMatri%2FBebe%2Fconjuntos%2F58_2.png?alt=media&token=b4492fa0-ac9e-488b-bb63-93fb871304ff",
                "https://firebasestorage.googleapis.com/v0/b/images-cdwenz.appspot.com/o/AmuriDiMatri%2FBebe%2Fconjuntos%2F58_3.png?alt=media&token=c9f732e4-4476-4ac5-b22f-01fb1cdeff06"
            ]
        },
        {
            "id": 59,
            "category": "Conjuntos",
            "name": "Conjunto 2P bordado koala",
            "brand": "Globito",
            "price": 38000,
            "description": "Conjunto 2 piezas body con catera bordado koala (body, pantalon)",
            "size": [
                "T1"
            ],
            "img": [
                "https://firebasestorage.googleapis.com/v0/b/images-cdwenz.appspot.com/o/AmuriDiMatri%2FBebe%2Fconjuntos%2F59_1.png?alt=media&token=a893a9a2-f835-4a49-ad4c-62a58babcfff",
                "https://firebasestorage.googleapis.com/v0/b/images-cdwenz.appspot.com/o/AmuriDiMatri%2FBebe%2Fconjuntos%2F59_2.png?alt=media&token=2c67fa28-1ed6-43e0-be81-7c260193424b",
                "https://firebasestorage.googleapis.com/v0/b/images-cdwenz.appspot.com/o/AmuriDiMatri%2FBebe%2Fconjuntos%2F59_3.png?alt=media&token=12538317-17f4-455d-ab15-ab479697151a"
            ]
        },
        {
            "id": 61,
            "category": "Conjuntos",
            "name": "Conjunto 2P musculosa rayada",
            "brand": "Globito",
            "price": 40000,
            "description": "Conjunto 2P musculosa rayada (musculosa, short)",
            "size": [
                "4A",
                "6A"
            ],
            "img": [
                "https://firebasestorage.googleapis.com/v0/b/images-cdwenz.appspot.com/o/AmuriDiMatri%2FBebe%2Fconjuntos%2F61_1.png?alt=media&token=e1a7cf37-7d84-44fb-bb50-2bdb6d44d1bd",
                "https://firebasestorage.googleapis.com/v0/b/images-cdwenz.appspot.com/o/AmuriDiMatri%2FBebe%2Fconjuntos%2F61_2.png?alt=media&token=c1d9d6c9-a004-4c7a-917b-2381e7d88422"
            ]
        },
        {
            "id": 62,
            "category": "Conjuntos",
            "name": "Conjunto 3P bordado ballena",
            "brand": "Globito",
            "price": 40000,
            "description": "Conjunto 3 piezas bordado ballena (body, pantalon, gorrito)",
            "size": [
                "T0",
                "T1"
            ],
            "img": [
                "https://firebasestorage.googleapis.com/v0/b/images-cdwenz.appspot.com/o/AmuriDiMatri%2FBebe%2Fconjuntos%2F62_1.png?alt=media&token=9044c6df-8333-4b53-a93a-b02c3f87cb7d"
            ]
        },
        {
            "id": 63,
            "category": "Conjuntos",
            "name": "Conjunto 3P bordado osito castillos",
            "brand": "Globito",
            "price": 40000,
            "description": "Conjunto 3P bordado osito castillos (body, pantalon, gorrito)",
            "size": [
                "T0"
            ],
            "img": [
                "https://firebasestorage.googleapis.com/v0/b/images-cdwenz.appspot.com/o/AmuriDiMatri%2FBebe%2Fconjuntos%2F63_1.jpeg?alt=media&token=b37381ed-688a-4100-9160-16a4812ab9a4"
            ]
        },
        {
            "id": 64,
            "category": "Conjuntos",
            "name": "Conjunto 3P bordado pirata",
            "brand": "Globito",
            "price": 40000,
            "description": "Conjunto 3P bordado pirata (body, pantalon, gorrito)",
            "size": [
                "T1"
            ],
            "img": [
                "https://firebasestorage.googleapis.com/v0/b/images-cdwenz.appspot.com/o/AmuriDiMatri%2FBebe%2Fconjuntos%2F64_1.png?alt=media&token=a8696726-3ff8-42c5-847e-d6f5073af704"
            ]
        },
        {
            "id": 66,
            "category": "Conjuntos",
            "name": "Conjunto remera c/ short lino",
            "brand": "Globito",
            "price": 45000,
            "description": "Conjunto remera c/ short lino",
            "size": [
                "3M",
                "6M",
                "9M",
                "12M",
                "18M",
                "24M"
            ],
            "img": [
                "https://firebasestorage.googleapis.com/v0/b/images-cdwenz.appspot.com/o/AmuriDiMatri%2FBebe%2Fconjuntos%2F66_1.png?alt=media&token=0dfb6637-df14-4cc4-82d8-c95a377903b7"
            ]
        },
        {
            "id": 67,
            "category": "Conjuntos",
            "name": "Conjunto remera c/ short lino",
            "brand": "Globito",
            "price": 45000,
            "description": "Conjunto remera c/ short lino",
            "size": [
                "12M",
                "18M",
                "24M",
                "4A",
                "6A"
            ],
            "img": [
                "https://firebasestorage.googleapis.com/v0/b/images-cdwenz.appspot.com/o/AmuriDiMatri%2FBebe%2Fconjuntos%2F67_1.png?alt=media&token=eb2763ea-15f9-4b7a-848f-ded5aad5fc69",
                "https://firebasestorage.googleapis.com/v0/b/images-cdwenz.appspot.com/o/AmuriDiMatri%2FBebe%2Fconjuntos%2F67_2.png?alt=media&token=154e6929-705e-4ddc-91a1-44329a4cce71",
                "https://firebasestorage.googleapis.com/v0/b/images-cdwenz.appspot.com/o/AmuriDiMatri%2FBebe%2Fconjuntos%2F67_3.png?alt=media&token=a953a4f2-8722-4fc0-b27f-2b946560e42a"
            ]
        },
        {
            "id": 69,
            "category": "Conjuntos",
            "name": "Conjunto 2P oveja",
            "brand": "Globito",
            "price": 46000,
            "description": "Conjunto 2P oveja (saquito, pantalon)",
            "size": [
                "6M",
                "9M",
                "12M"
            ],
            "img": [
                "https://firebasestorage.googleapis.com/v0/b/images-cdwenz.appspot.com/o/AmuriDiMatri%2FBebe%2Fconjuntos%2F69_1.png?alt=media&token=c47f8c1c-d4bf-4f69-a54c-4c8869c39258",
                "https://firebasestorage.googleapis.com/v0/b/images-cdwenz.appspot.com/o/AmuriDiMatri%2FBebe%2Fconjuntos%2F69_2.png?alt=media&token=dc210833-a484-4012-b9ca-5f840acbe705"
            ]
        },
        {
            "id": 70,
            "category": "Conjuntos",
            "name": "Jardinero c/ remera lino",
            "brand": "Globito",
            "price": 38000,
            "description": "Jardinero c/ remera lino",
            "size": [
                "0M",
                "6M",
                "9M"
            ],
            "img": [
                "https://firebasestorage.googleapis.com/v0/b/images-cdwenz.appspot.com/o/AmuriDiMatri%2FBebe%2Fconjuntos%2F70_1.png?alt=media&token=a3a101cb-05e1-46ff-b46b-7528fea8b081"
            ]
        },
        {
            "id": 71,
            "category": "Conjuntos",
            "name": "Jardinero c/ remera ballena",
            "brand": "Globito",
            "price": 38000,
            "description": "Jardinero c/ remera ballena",
            "size": [
                "3M"
            ],
            "img": [
                "https://firebasestorage.googleapis.com/v0/b/images-cdwenz.appspot.com/o/AmuriDiMatri%2FBebe%2Fconjuntos%2F71_1.png?alt=media&token=12b382b2-9c13-4d45-a715-e96b1da2ce19"
            ]
        },
        {
            "id": 72,
            "category": "Conjuntos",
            "name": "Jardinero c/ remera pez",
            "brand": "Globito",
            "price": 38000,
            "description": "Jardinero c/ remera pez",
            "size": [
                "T0",
                ""
            ],
            "img": [
                "https://firebasestorage.googleapis.com/v0/b/images-cdwenz.appspot.com/o/AmuriDiMatri%2FBebe%2Fconjuntos%2F72_1.png?alt=media&token=57ae980d-09e8-4140-9437-eea2e3ddf762"
            ]
        },
        {
            "id": 73,
            "category": "Conjuntos",
            "name": "Jardinero c/ remera",
            "brand": "Globito",
            "price": 42000,
            "description": "Jardinero c/ remera",
            "size": [
                "3M",
                "6M"
            ],
            "img": [
                "https://firebasestorage.googleapis.com/v0/b/images-cdwenz.appspot.com/o/AmuriDiMatri%2FBebe%2Fconjuntos%2F73_1.png?alt=media&token=2d729a77-8de7-4e9d-a73a-9082db8549af",
                "https://firebasestorage.googleapis.com/v0/b/images-cdwenz.appspot.com/o/AmuriDiMatri%2FBebe%2Fconjuntos%2F73_2.png?alt=media&token=8996cc1f-a8dd-43ae-90e6-41d1f8d3b6b7"
            ]
        },
        {
            "id": 74,
            "category": "Conjuntos",
            "name": "Conjunto 2P bordado Argentina",
            "brand": "Globito",
            "price": 38000,
            "description": "Conjunto 2p bordado Argentina (short, remera)",
            "size": [
                "3M"
            ],
            "img": [
                "https://firebasestorage.googleapis.com/v0/b/images-cdwenz.appspot.com/o/AmuriDiMatri%2FBebe%2Fconjuntos%2F74_1.png?alt=media&token=155f21b8-ea40-4070-af2b-6f5dc1b76fc7",
                "https://firebasestorage.googleapis.com/v0/b/images-cdwenz.appspot.com/o/AmuriDiMatri%2FBebe%2Fconjuntos%2F74_2.png?alt=media&token=f66cfe54-2d45-4741-87c9-f2157bf6f277"
            ]
        },
        {
            "id": 75,
            "category": "Remeras",
            "name": "Remera polito de algodon con logo Lucas",
            "brand": "Magdalena Esposito",
            "price": 45000,
            "description": "Remera polito de algodon con logo Lucas",
            "size": [
                "12M",
                "18M",
                "24M",
                "4A"
            ],
            "img": [
                "https://firebasestorage.googleapis.com/v0/b/images-cdwenz.appspot.com/o/AmuriDiMatri%2FBebe%2Fremeras%2F75_1.png?alt=media&token=25133603-23e8-4300-8b88-c2e8793d1bd9"
            ]
        },
        {
            "id": 76,
            "category": "Remeras",
            "name": "Remera polito de algodon con logo Lucas",
            "brand": "Magdalena Esposito",
            "price": 45000,
            "description": "Remera polito de algodon con logo Lucas",
            "size": [
                "12M",
                "18M",
                "24M",
                "4A",
                "6A"
            ],
            "img": [
                "https://firebasestorage.googleapis.com/v0/b/images-cdwenz.appspot.com/o/AmuriDiMatri%2FBebe%2Fremeras%2F76_1.png?alt=media&token=616f0959-f641-4c48-8d18-9e1e86ccae90"
            ]
        },
        {
            "id": 77,
            "category": "Remeras",
            "name": "Remera de pique de algodon combinada Thomas",
            "brand": "Magdalena Esposito",
            "price": 45000,
            "description": "Remera de pique de algodon combinada Thomas",
            "size": [
                "24M"
            ],
            "img": [
                "https://firebasestorage.googleapis.com/v0/b/images-cdwenz.appspot.com/o/AmuriDiMatri%2FBebe%2Fremeras%2F77_1.png?alt=media&token=0d63d85c-a689-466d-8440-6995444512a0"
            ]
        },
        {
            "id": 78,
            "category": "Remeras",
            "name": "Remera de algodon flame con carterita y bolsillo Trent",
            "brand": "Magdalena Esposito",
            "price": 35000,
            "description": "Remera de algodon flame con carterita y bolsillo Trent",
            "size": [
                "24M"
            ],
            "img": [
                "https://firebasestorage.googleapis.com/v0/b/images-cdwenz.appspot.com/o/AmuriDiMatri%2FBebe%2Fremeras%2F78_1.png?alt=media&token=f593bc9e-3f88-4db5-b5ff-1dfb53b615f0"
            ]
        },
        {
            "id": 79,
            "category": "Remeras",
            "name": "Remera de algodon con escote redondo y logo",
            "brand": "Magdalena Esposito",
            "price": 30000,
            "description": "Remera de algodon con escote redondo y logo",
            "size": [
                "12M",
                "18M",
                "6A"
            ],
            "img": [
                "https://firebasestorage.googleapis.com/v0/b/images-cdwenz.appspot.com/o/AmuriDiMatri%2FBebe%2Fremeras%2F79_1.png?alt=media&token=b86f0b67-a302-4ac5-8e5a-5216c84cf2b5"
            ]
        },
        {
            "id": 80,
            "category": "Remeras",
            "name": "Remera de algodon con escote redondo y logo",
            "brand": "Magdalena Esposito",
            "price": 30000,
            "description": "Remera de algodon con escote redondo y logo",
            "size": [
                "18M",
                "24M",
                "4A"
            ],
            "img": [
                "https://firebasestorage.googleapis.com/v0/b/images-cdwenz.appspot.com/o/AmuriDiMatri%2FBebe%2Fremeras%2F80_1.png?alt=media&token=2f1ad610-b47a-4cfe-b0fa-e13386df13e6"
            ]
        },
        {
            "id": 81,
            "category": "Remeras",
            "name": "Remera marinera",
            "brand": "Globito",
            "price": 22000,
            "description": "Remera manga corta marinera",
            "size": [
                "12M",
                "4A"
            ],
            "img": [
                "https://firebasestorage.googleapis.com/v0/b/images-cdwenz.appspot.com/o/AmuriDiMatri%2FBebe%2Fremeras%2F81_1.png?alt=media&token=1c921b9e-3098-4cbd-a1d3-4b7f96c1df85"
            ]
        },
        {
            "id": 83,
            "category": "Remeras",
            "name": "Remera elefante",
            "brand": "Old Bunch",
            "price": 25000,
            "description": "Remera elefante",
            "size": [
                "2A",
                "4A"
            ],
            "img": [
                "https://firebasestorage.googleapis.com/v0/b/images-cdwenz.appspot.com/o/AmuriDiMatri%2FBebe%2Fremeras%2F83_1.png?alt=media&token=6e115c52-2ef2-4ef6-9a72-09446190d416"
            ]
        },
        {
            "id": 84,
            "category": "Remeras",
            "name": "Remera pulpo",
            "brand": "Old Bunch",
            "price": 25000,
            "description": "Remera pulpo",
            "size": [
                "4A"
            ],
            "img": [
                "https://firebasestorage.googleapis.com/v0/b/images-cdwenz.appspot.com/o/AmuriDiMatri%2FBebe%2Fremeras%2F84_1.png?alt=media&token=6ac7bd08-512c-4cdf-84a8-81be7512b719"
            ]
        },
        {
            "id": 85,
            "category": "Remeras",
            "name": "Remera pique polo",
            "brand": "Old Bunch",
            "price": 35000,
            "description": "Remera pique polo",
            "size": [
                "1A",
                "2A",
                "4A"
            ],
            "img": [
                "https://firebasestorage.googleapis.com/v0/b/images-cdwenz.appspot.com/o/AmuriDiMatri%2FBebe%2Fremeras%2F85_1.png?alt=media&token=424716ff-3336-4d16-af5b-cc8143a4f30b"
            ]
        },
        {
            "id": 86,
            "category": "Remeras",
            "name": "Musculosa rayada",
            "brand": "Globito",
            "price": 22000,
            "description": "Musculosa rayada",
            "size": [
                "6A"
            ],
            "img": [
                "https://firebasestorage.googleapis.com/v0/b/images-cdwenz.appspot.com/o/AmuriDiMatri%2FBebe%2Fremeras%2F86_1.png?alt=media&token=018e1464-e0a3-4063-bf30-e88704258f04"
            ]
        },
        {
            "id": 87,
            "category": "Camperas",
            "name": "Mini blazer de algodon Roger",
            "brand": "Magdalena Esposito",
            "price": 90000,
            "description": "Mini blazer de algodon Roger",
            "size": [
                "12M"
            ],
            "img": [
                "https://firebasestorage.googleapis.com/v0/b/images-cdwenz.appspot.com/o/AmuriDiMatri%2FBebe%2Fcamperas%2F87_1.png?alt=media&token=45fe9001-6e89-4f3a-825a-c5c0009497a8"
            ]
        },
        {
            "id": 88,
            "category": "Camperas",
            "name": "Mini blazer de algodon Roger",
            "brand": "Magdalena Esposito",
            "price": 90000,
            "description": "Mini blazer de algodon Roger",
            "size": [
                "12M"
            ],
            "img": [
                "https://firebasestorage.googleapis.com/v0/b/images-cdwenz.appspot.com/o/AmuriDiMatri%2FBebe%2Fcamperas%2F88_1.png?alt=media&token=d5596b85-4cca-4006-98ba-97266850d156"
            ]
        },
        {
            "id": 89,
            "category": "Camperas",
            "name": "Saco con bolsillos combinado escote en V Lucas",
            "brand": "Magdalena Esposito",
            "price": 85000,
            "description": "Saco con bolsillos combinado escote en V Lucas",
            "size": [
                "24M"
            ],
            "img": [
                "https://firebasestorage.googleapis.com/v0/b/images-cdwenz.appspot.com/o/AmuriDiMatri%2FBebe%2Fcamperas%2F89_1.png?alt=media&token=ad18fb35-f1c9-495c-b90b-a76f9c212ac2"
            ]
        },
        {
            "id": 90,
            "category": "Camperas",
            "name": "Buzo de rustico estampado San Diego",
            "brand": "Magdalena Esposito",
            "price": 60000,
            "description": "Buzo de rustico estampado San Diego",
            "size": [
                "24M",
                "6A"
            ],
            "img": [
                "https://firebasestorage.googleapis.com/v0/b/images-cdwenz.appspot.com/o/AmuriDiMatri%2FBebe%2Fcamperas%2F90_1.png?alt=media&token=efbc9af3-0fd3-4ecb-ba15-da7267880cf5"
            ]
        },
        {
            "id": 91,
            "category": "Camperas",
            "name": "Miniblazer Dodi",
            "brand": "Magdalena Esposito",
            "price": 80000,
            "description": "Miniblazer Dodi",
            "size": [
                "18M"
            ],
            "img": [
                "https://firebasestorage.googleapis.com/v0/b/images-cdwenz.appspot.com/o/AmuriDiMatri%2FBebe%2Fcamperas%2F91_1.png?alt=media&token=aacb601f-4763-46ff-9d56-e2a16e34bc07"
            ]
        },
        {
            "id": 92,
            "category": "Camperas",
            "name": "Saco aran con cuello Smocking Borja",
            "brand": "Magdalena Esposito",
            "price": 80000,
            "description": "Saco aran con cuello Smocking Borja",
            "size": [
                "24M"
            ],
            "img": [
                "https://firebasestorage.googleapis.com/v0/b/images-cdwenz.appspot.com/o/AmuriDiMatri%2FBebe%2Fcamperas%2F92_1.png?alt=media&token=e20751f7-f0dc-4f04-bce1-6642495f5a32"
            ]
        },
        {
            "id": 93,
            "category": "Camperas",
            "name": "Campera de plush forrada con piel Power",
            "brand": "Magdalena Esposito",
            "price": 80000,
            "description": "Campera de plush forrada con piel Power",
            "size": [
                "12M",
                "18M"
            ],
            "img": [
                "https://firebasestorage.googleapis.com/v0/b/images-cdwenz.appspot.com/o/AmuriDiMatri%2FBebe%2Fcamperas%2F93_1.png?alt=media&token=3dc76ed7-da61-4bf7-9955-ec0dbc3ea4ed"
            ]
        },
        {
            "id": 94,
            "category": "Camperas",
            "name": "Buzo de friza estampado California",
            "brand": "Magdalena Esposito",
            "price": 60000,
            "description": "Buzo de friza estampado California",
            "size": [
                "6A"
            ],
            "img": [
                "https://firebasestorage.googleapis.com/v0/b/images-cdwenz.appspot.com/o/AmuriDiMatri%2FBebe%2Fcamperas%2F94_1.png?alt=media&token=91fa3b50-6e12-46c6-8dfe-3dd21ddc9d3d"
            ]
        },
        {
            "id": 95,
            "category": "Pantalones",
            "name": "Pantalon de jeans varon Mica",
            "brand": "Magdalena Esposito",
            "price": 65000,
            "description": "Pantalon de jeans varon Mica",
            "size": [
                "24M",
                "4A",
                "6A"
            ],
            "img": [
                "https://firebasestorage.googleapis.com/v0/b/images-cdwenz.appspot.com/o/AmuriDiMatri%2FBebe%2Fpantalones%2F95_1.png?alt=media&token=3324c9de-cab1-4b37-a2d0-70f015244ca0"
            ]
        },
        {
            "id": 96,
            "category": "Pantalones",
            "name": "Pantalon de gabardina liviana Nico",
            "brand": "Magdalena Esposito",
            "price": 72500,
            "description": "Pantalon de gabardina liviana Nico",
            "size": [
                "18M",
                "24M",
                "6A"
            ],
            "img": [
                "https://firebasestorage.googleapis.com/v0/b/images-cdwenz.appspot.com/o/AmuriDiMatri%2FBebe%2Fpantalones%2F96_1.png?alt=media&token=54bcf14b-a9ed-431f-ae9c-bf7ebbc2d180"
            ]
        },
        {
            "id": 97,
            "category": "Pantalones",
            "name": "Pantalon de gabardina con recortes y bolsillo plaque en la espalda",
            "brand": "Magdalena Esposito",
            "price": 72500,
            "description": "Pantalon de gabardina con recortes y bolsillo plaque en la espalda",
            "size": [
                "18M",
                "24M",
                "6A"
            ],
            "img": [
                "https://firebasestorage.googleapis.com/v0/b/images-cdwenz.appspot.com/o/AmuriDiMatri%2FBebe%2Fpantalones%2F97_1.png?alt=media&token=e7b3bda4-26ce-47ff-a2e9-09b03688dec7"
            ]
        },
        {
            "id": 98,
            "category": "Pantalones",
            "name": "Pantalon de gabardina Lucas",
            "brand": "Magdalena Esposito",
            "price": 45000,
            "description": "Pantalon de gabardina Lucas",
            "size": [
                "24M"
            ],
            "img": [
                "https://firebasestorage.googleapis.com/v0/b/images-cdwenz.appspot.com/o/AmuriDiMatri%2FBebe%2Fpantalones%2F98_1.png?alt=media&token=e494930d-9203-4357-b83c-966032b113e7"
            ]
        },
        {
            "id": 99,
            "category": "Pantalones",
            "name": "Pantalon mini chino",
            "brand": "Old Bunch",
            "price": 35000,
            "description": "Pantalon mini chino",
            "size": [
                "12M",
                "18M"
            ],
            "img": [
                "https://firebasestorage.googleapis.com/v0/b/images-cdwenz.appspot.com/o/AmuriDiMatri%2FBebe%2Fpantalones%2F99_1.png?alt=media&token=6c72c15f-f36d-4a5a-bb22-e757efea460f"
            ]
        },
        {
            "id": 100,
            "category": "Mantas",
            "name": "Conjunto elefante celeste",
            "brand": "Botonitos",
            "price": 45000,
            "description": "Conjunto (manta, babita, babero, escarpin) elefante celeste",
            "size": [
                "Unico"
            ],
            "img": [
                "https://firebasestorage.googleapis.com/v0/b/images-cdwenz.appspot.com/o/AmuriDiMatri%2FBebe%2Fmantas%2F100_1.png?alt=media&token=b8e38a0d-6b0c-4d47-a5a2-bb71a389077b"
            ]
        },
        {
            "id": 101,
            "category": "Mantas",
            "name": "Conjunto nautico",
            "brand": "Botonitos",
            "price": 45000,
            "description": "Conjunto (manta, babita, babero, escarpin) nautico",
            "size": [
                "Unico"
            ],
            "img": [
                "https://firebasestorage.googleapis.com/v0/b/images-cdwenz.appspot.com/o/AmuriDiMatri%2FBebe%2Fmantas%2F101_1.png?alt=media&token=92726f63-2c29-41a2-904b-d8ba105f0be5"
            ]
        },
        {
            "id": 102,
            "category": "Mantas",
            "name": "Conjunto safari",
            "brand": "Botonitos",
            "price": 45000,
            "description": "Conjunto (manta, babita, babero, escarpin) safari",
            "size": [
                "Unico"
            ],
            "img": [
                "https://firebasestorage.googleapis.com/v0/b/images-cdwenz.appspot.com/o/AmuriDiMatri%2FBebe%2Fmantas%2F102_1.png?alt=media&token=b81cfd54-f957-49b2-8ef0-a6fe8cee6590"
            ]
        },
        {
            "id": 103,
            "category": "Mantas",
            "name": "Conjunto raya natural",
            "brand": "Botonitos",
            "price": 45000,
            "description": "Conjunto (manta, babita, babero, escarpin) raya natural",
            "size": [
                "Unico"
            ],
            "img": [
                "https://firebasestorage.googleapis.com/v0/b/images-cdwenz.appspot.com/o/AmuriDiMatri%2FBebe%2Fmantas%2F103_1.png?alt=media&token=cac2b913-f212-423d-90e8-1fb38d019005"
            ]
        },
        {
            "id": 104,
            "category": "Accesorios",
            "name": "Babitas (marinero, flores, rayado)",
            "brand": "Globito",
            "price": 20000,
            "description": "Babitas (marinero, flores, rayado)",
            "size": [
                "Unico"
            ],
            "img": [
                "https://firebasestorage.googleapis.com/v0/b/images-cdwenz.appspot.com/o/AmuriDiMatri%2FBebe%2Faccesorios%2F104_1.png?alt=media&token=f835f37c-b982-4b6e-b94d-efb07808f4ae"
            ]
        },
        {
            "id": 105,
            "category": "Accesorios",
            "name": "Conjunto 3P conejo",
            "brand": "Globito",
            "price": 15000,
            "description": "Conjunto 3P conejo (sonajero, porta chupete, mordillo)",
            "size": [
                "Unico"
            ],
            "img": [
                "https://firebasestorage.googleapis.com/v0/b/images-cdwenz.appspot.com/o/AmuriDiMatri%2FBebe%2Faccesorios%2F105_1.png?alt=media&token=4f457304-f93c-47b0-b9eb-6053fae2e94f"
            ]
        },
        {
            "id": 106,
            "category": "Accesorios",
            "name": "Conjunto bordado zorro",
            "brand": "Globito",
            "price": 15000,
            "description": "Conjunto bordado zorro (trapito, babero)",
            "size": [
                "Unico"
            ],
            "img": [
                "https://firebasestorage.googleapis.com/v0/b/images-cdwenz.appspot.com/o/AmuriDiMatri%2FBebe%2Faccesorios%2F106_1.png?alt=media&token=1c540035-0a15-4f36-a71b-f32b3b5d0083"
            ]
        },
        {
            "id": 107,
            "category": "Juguetes",
            "name": "Torre apilable",
            "brand": "Mis Creaciones",
            "price": 25000,
            "description": "Torre apilable",
            "size": [
                "N/A"
            ],
            "img": [
                "https://firebasestorage.googleapis.com/v0/b/images-cdwenz.appspot.com/o/AmuriDiMatri%2FBebe%2Fjuguetes%2F107_1.png?alt=media&token=c53f432c-5c26-4850-bad9-253b38c9e464"
            ]
        },
        {
            "id": 108,
            "category": "Juguetes",
            "name": "Carro de arrastre",
            "brand": "Mis Creaciones",
            "price": 40000,
            "description": "Carro de arrastre con 30 bloques de colores",
            "size": [
                "N/A"
            ],
            "img": [
                "https://firebasestorage.googleapis.com/v0/b/images-cdwenz.appspot.com/o/AmuriDiMatri%2FBebe%2Fjuguetes%2F108_1.png?alt=media&token=7d18dcbe-565d-412f-961c-b541f775560d",
                "https://firebasestorage.googleapis.com/v0/b/images-cdwenz.appspot.com/o/AmuriDiMatri%2FBebe%2Fjuguetes%2F108_2.png?alt=media&token=fc43281c-615c-4404-a630-da8dcbfbb716",
                "https://firebasestorage.googleapis.com/v0/b/images-cdwenz.appspot.com/o/AmuriDiMatri%2FBebe%2Fjuguetes%2F108_3.png?alt=media&token=4a5fd8de-2113-4c77-9d5b-f0112b80041a"
            ]
        },
        {
            "id": 109,
            "category": "Juguetes",
            "name": "Jenga gigante con banquito",
            "brand": "Mis Creaciones",
            "price": 80000,
            "description": "Jenga gigante de colores con banquito y cajon de guardado",
            "size": [
                "N/A"
            ],
            "img": [
                "https://firebasestorage.googleapis.com/v0/b/images-cdwenz.appspot.com/o/AmuriDiMatri%2FBebe%2Fjuguetes%2F109_1.png?alt=media&token=308e8573-66a3-46e6-a84d-56905c8e8578",
                "https://firebasestorage.googleapis.com/v0/b/images-cdwenz.appspot.com/o/AmuriDiMatri%2FBebe%2Fjuguetes%2F109_2.png?alt=media&token=ad955086-9002-436a-a819-a151635d0b5f"
            ]
        }
    ]
}